thonnycontrib/thonny_astro_pi_replay.py
thonnycontrib/res/AstroPi_2021_colour.png
thonny_astro_pi_replay-0.0.5.dist-info/LICENCE.txt
thonny_astro_pi_replay-0.0.5.dist-info/METADATA
thonny_astro_pi_replay-0.0.5.dist-info/WHEEL
thonny_astro_pi_replay-0.0.5.dist-info/top_level.txt
thonny_astro_pi_replay-0.0.5.dist-info/RECORD
