Metadata-Version: 2.1
Name: thonny-astro-pi-replay
Version: 0.0.5
Summary: A Thonny plugin to use the Astro Pi Replay tool
Author-email: Geraint Ballinger <geraint.ballinger@raspberrypi.org>
Project-URL: Homepage, https://github.com/astro-pi/Astro-Pi-Replay
Classifier: Programming Language :: Python :: 3
Classifier: Operating System :: OS Independent
Requires-Python: >=3.9
License-File: LICENCE.txt
Requires-Dist: thonny >=3.1.2
Requires-Dist: astro-pi-replay >=0.0.17
